mllam_data_prep-0.7.0.dist-info/METADATA
mllam_data_prep-0.7.0.dist-info/WHEEL
mllam_data_prep-0.7.0.dist-info/entry_points.txt
mllam_data_prep/__init__.py
mllam_data_prep/__main__.py
mllam_data_prep/cli.py
mllam_data_prep/config.py
mllam_data_prep/create_dataset.py
mllam_data_prep/ops/__init__.py
mllam_data_prep/ops/chunking.py
mllam_data_prep/ops/cropping.py
mllam_data_prep/ops/derive_variable/__init__.py
mllam_data_prep/ops/derive_variable/main.py
mllam_data_prep/ops/derive_variable/physical_field.py
mllam_data_prep/ops/derive_variable/time_components.py
mllam_data_prep/ops/loading.py
mllam_data_prep/ops/mapping.py
mllam_data_prep/ops/selection.py
mllam_data_prep/ops/stacking.py
mllam_data_prep/ops/statistics.py
mllam_data_prep/ops/subsetting.py
mllam_data_prep-0.7.0.dist-info/RECORD
