Metadata-Version: 2.1
Name: mllam-data-prep
Version: 0.7.0
Summary: dataset preparation for data-driven weather models
Author-Email: Leif Denby <lcd@dmi.dk>, Hauke Schulz <has@dmi.dk>, Emy Alerskans <ea@dmi.dk>, Eleni Briola <elb@dmi.dk>, Joel Oskarsson <joel.oskarsson@liu.se>, Kashif Rasul <kashif.rasul@gmail.com>, Jordan Matelsky <opensource@matelsky.com>, =?utf-8?q?Martin_Fr=C3=B8lund?= <maf@dmi.dk>, Simon Kamuk Christiansen <skc@dmi.dk>
License: MIT
Requires-Python: >=3.9
Requires-Dist: xarray>=2024.2.0
Requires-Dist: zarr>=2.17.0
Requires-Dist: pyyaml>=6.0.1
Requires-Dist: loguru>=0.7.2
Requires-Dist: isodate>=0.6.1
Requires-Dist: requests>=2.31.0
Requires-Dist: aiohttp>=3.9.3
Requires-Dist: dataclass-wizard>=0.29.2
Requires-Dist: semver>=3.0.2
Requires-Dist: rich>=13.7.1
Requires-Dist: dask>=2024.2.1
Requires-Dist: psutil>=5.7.2
Requires-Dist: packaging>=23.1
Requires-Dist: deepdiff>=8.2.0
Requires-Dist: spherical-geometry>=1.3.2
Requires-Dist: cartopy>=0.23.0
Requires-Dist: gcsfs>=2024.10.0
Requires-Dist: jinja2>=3.1.4
Provides-Extra: dask-distributed
Requires-Dist: dask[distributed]>=2024.7.1; extra == "dask-distributed"
Requires-Dist: bokeh!=3.0.*,>=2.4.2; extra == "dask-distributed"
